identy.py
identy-0.0.4.dist-info/LICENSE
identy-0.0.4.dist-info/METADATA
identy-0.0.4.dist-info/WHEEL
identy-0.0.4.dist-info/top_level.txt
identy-0.0.4.dist-info/RECORD
