Metadata-Version: 2.1
Name: identy
Version: 0.0.4
Summary: Generate grayscale identity icons.
Home-page: https://github.com/onerbs/identy
Author: AAAA
Author-email: dev@onerbs.com
License: MIT
Keywords: identicon png
Platform: UNKNOWN
Classifier: Development Status :: 3 - Alpha
Classifier: Intended Audience :: Developers
Classifier: License :: OSI Approved :: MIT License
Classifier: Operating System :: OS Independent
Classifier: Programming Language :: Python :: 3.8
Classifier: Programming Language :: Python :: 3.9
Classifier: Topic :: Software Development :: Libraries :: Python Modules
Requires-Dist: xu
